ntnput/__init__.py
ntnput/misc.py
ntnput-2.6.0.dist-info/WHEEL
ntnput-2.6.0.dist-info/entry_points.txt
ntnput-2.6.0.dist-info/METADATA
ntnput-2.6.0.dist-info/RECORD
