Metadata-Version: 2.3
Name: ntnput
Version: 2.6.0
Summary: Minimalist Python library using wraps of undocumented `Nt` functions to interact with mouse and keyboard stealthy
Author: Xenely
Requires-Python: >=3.10
